guilded/__init__.py
guilded/abc.py
guilded/asset.py
guilded/backoff.py
guilded/category.py
guilded/channel.py
guilded/client.py
guilded/colour.py
guilded/embed.py
guilded/emote.py
guilded/enums.py
guilded/errors.py
guilded/events.py
guilded/file.py
guilded/flowbot.py
guilded/gateway.py
guilded/group.py
guilded/http.py
guilded/invite.py
guilded/message.py
guilded/mixins.py
guilded/override.py
guilded/permissions.py
guilded/presence.py
guilded/reaction.py
guilded/reply.py
guilded/role.py
guilded/server.py
guilded/status.py
guilded/subscription.py
guilded/user.py
guilded/utils.py
guilded/ext/commands/__init__.py
guilded/ext/commands/_types.py
guilded/ext/commands/bot.py
guilded/ext/commands/cog.py
guilded/ext/commands/context.py
guilded/ext/commands/converters.py
guilded/ext/commands/cooldowns.py
guilded/ext/commands/core.py
guilded/ext/commands/errors.py
guilded/ext/commands/help.py
guilded/ext/commands/view.py
guilded/ext/tasks/__init__.py
guilded/types/announcement.py
guilded/types/asset.py
guilded/types/calendar_event.py
guilded/types/category.py
guilded/types/channel.py
guilded/types/comment.py
guilded/types/doc.py
guilded/types/embed.py
guilded/types/emote.py
guilded/types/forum_topic.py
guilded/types/gateway.py
guilded/types/group.py
guilded/types/http.py
guilded/types/list_item.py
guilded/types/message.py
guilded/types/reaction.py
guilded/types/role.py
guilded/types/server.py
guilded/types/social_link.py
guilded/types/subscription.py
guilded/types/user.py
guilded/types/webhook.py
guilded/webhook/__init__.py
guilded/webhook/async_.py
guilded.py-1.13.3.dist-info/LICENSE
guilded.py-1.13.3.dist-info/METADATA
guilded.py-1.13.3.dist-info/WHEEL
guilded.py-1.13.3.dist-info/top_level.txt
guilded.py-1.13.3.dist-info/RECORD
