Metadata-Version: 2.1
Name: guilded.py
Version: 1.13.3
Summary: An API wrapper in Python for Guilded's bot API
Home-page: https://github.com/shayypy/guilded.py
Author: shay (shayypy)
License: MIT
Project-URL: Documentation, https://guildedpy.readthedocs.io/en/latest/
Project-URL: Issue tracker, https://github.com/shayypy/guilded.py/issues
Platform: UNKNOWN
Classifier: Programming Language :: Python :: 3.8
Classifier: Programming Language :: Python :: 3.9
Classifier: Programming Language :: Python :: 3.10
Classifier: License :: OSI Approved :: MIT License
Classifier: Operating System :: OS Independent
Classifier: Natural Language :: English
Requires-Python: >=3.8.0
License-File: LICENSE
Requires-Dist: aiohttp
Provides-Extra: docs
Requires-Dist: sphinx==4.4.0; extra == "docs"
Requires-Dist: sphinxcontrib-trio==1.1.2; extra == "docs"
Requires-Dist: sphinxcontrib-websupport; extra == "docs"
Requires-Dist: typing-extensions<5,>=4.3; extra == "docs"
